revise/__init__.py
revise/keras.py
revise_x-0.0.3.dist-info/METADATA
revise_x-0.0.3.dist-info/RECORD
revise_x-0.0.3.dist-info/WHEEL
revise_x-0.0.3.dist-info/top_level.txt
