Metadata-Version: 2.1
Name: revise-x
Version: 0.0.3
Summary: An exporter for trained neural networks built with keras to work with revise projects
Home-page: https://github.com/noheltcj/revise-x
License: UNKNOWN
Project-URL: Bug Reports, https://github.com/noheltcj/revise-x/issues
Project-URL: Source, https://github.com/noheltcj/revise-x
Keywords: revise machine_learning exporter keras
Platform: UNKNOWN
Classifier: Development Status :: 3 - Alpha
Classifier: Intended Audience :: Developers
Classifier: Topic :: Software Development :: Build Tools
Classifier: License :: OSI Approved :: MIT License
Classifier: Programming Language :: Python :: 3.5
Classifier: Programming Language :: Python :: 3.6
Requires-Python: >=3.5
